[{"text": "Best-Performing Leveraged ETF Areas of Last Week Sanghamitra Saha Wed, Jan 22, 2025, 8:12 AM 4 min read In This Article: COIN -2.38% MSTR +3.67% ^GSPC -0.76% Wall Street was upbeat last week with the S&P 500 adding about 2.9%, the Dow Jones gaining about 3.7% and the Nasdaq Composite advancing about 2.5%. Both the Dow Jones and the S&P 500 indexes posted their biggest weekly advance since the week of the U.S. presidential election in November. Retail sales grew at a slower pace than Wall Street had expected in December. This has probably triggered hopes for a dovish Fed in the near term, which in turn boosted the broader market (read: 4 ETF Sectors to Win Despite Moderate Retail Sales in December). Gaza truce, easing inflation and solid bank earnings also contributed to the Wall Street gains. Most big banks came up with upbeat earnings last week (read: ETFs to Play on Gaza Truce, Easing Inflation & Solid Bank Earnings). Find the latest earnings estimates and surprises on Zacks Earnings Calendar . Cooling Inflation The annual inflation rate in the United States rose for the 3rd consecutive month to 2.9% in December 2024 from 2.7% in November, in line with market expectations. This year-end rise is partly driven by low base effects from last year, particularly for energy. Gaza Ceasefire Agreement Reached On Wednesday, Israel and Hamas finalized a ceasefire and hostage release deal aimed at ending the 15-month war in the Gaza Strip. The conflict has caused widespread devastation and inflamed regional tensions. the deal's implementation would occur in three phases. The deal is built on a framework proposed by the Biden administration in May. Moderate Retail Sales in December Retail sales grew at a slower pace than Wall Street had expected in December. Retail sales rose 0.4% sequentially in December. Economists had expected a 0.6% rise in spending, according to Bloomberg data. Meanwhile, retail sales in November were revised up to 0.8% from a prior reading that showed a 0.7% increase in the month, according to Census Bureau data (read: 4 ETF Sectors to Win Despite Moderate Retail Sales in December). Bitcoin Stages Rebound Bitcoin staged a rebound last week with about 9% gains. Most securities that are linked to Bitcoin mining and trading recorded gains in prices. For example, MicroStrategy Inc MSTR, the world\u2019s largest Bitcoin hoarder, shares surged about 28% last week. Shares of Coinbase Global Inc. COIN, which operates a cryptocurrency exchange platform, jumped about 20% last week (read: Will MicroStrategy ETFs Get a Boost from the Nasdaq-100 Joining?). Winning ETFs in Focus Against this backdrop, below we highlight a few leveraged exchange-traded funds (ETFs) that gained last week. Story Continues Bull-MSTR \u2013 Defiance Daily Target 2x Long MSTR ETF ( MSTX ) \u2013 Up 43.7% The Defiance Daily Target 2X Long MSTR ETF seeks daily leveraged investment results of 2x the daily percentage change in the share price of MicroStrategy Incorporated. The expense ratio of the ETF is 1.29% annually. Bull Coinbase \u2013 GraniteShares 2x Long COIN Daily ETF ( CONL ) \u2013 Up 28.5% The GraniteShares 2x Long COIN Daily ETF seeks daily investment results, before fees and expenses, of 2 times the daily percentage change of the common stock of Coinbase Global Inc. The expense ratio of the ETF is 1.15% annually. Bull Homebuilders \u2013 Direxion Daily Homebuilders & Supplies Bull 3X Shares ( NAIL ) \u2013 Up 26.8% The Direxion Daily Homebuilders & Supplies Bull 3X Shares seeks daily investment results, before fees and expenses, of 300% of the performance of the Dow Jones U.S. Select Home Construction Index, which measures U.S companies in the home construction sector that provide a wide range of products and services related to homebuilding. The expense ratio is 0.97%. Bull Regional Banks \u2013 Direxion Daily Regional Banks Bull 3X Shares ( DPST ) \u2013 Up 25.4% The Direxion Daily Regional Banks Bull 3x Shares seeks daily investment results, before fees and expenses, of 300% of the performance of the S&P Regional Banks Select Industry Index. The expense ratio of the ETF is 0.95% annually. Bull Bitcoin \u2013 ProShares Ultra Bitcoin ETF ( BITU ) \u2013 Up 21.7% The ProShares Ultra Bitcoin ETF seeks daily investment results that correspond, before fees and expenses, to 2X the daily performance of the Bloomberg Bitcoin Index. The ETF charges 95 bps in fees. Want the latest recommendations from Zacks Investment Research? Today, you can download 7 Best Stocks for the Next 30 Days. Click to get this free report MicroStrategy Incorporated (MSTR) : Free Stock Analysis Report Coinbase Global, Inc. (COIN) : Free Stock Analysis Report To read this article on Zacks.com click here. Zacks Investment Research View Comments Terms and Privacy Policy Privacy Dashboard Recommended Stories", "symbol": "BITU", "date": "2025-01-22T05:12:00+00:00", "sentiment": {"score": 0.8957857973873615, "confidence": 0.9367610216140747, "probabilities": {"positive": 0.9367610216140747, "negative": 0.04097522422671318, "neutral": 0.022263726219534874}}, "embedding": [-0.02769296057522297, -0.034020133316516876, 0.0023650918155908585, 0.0751914456486702, 0.08044446259737015, -0.06381289660930634, -0.11036793142557144, 0.0041448092088103294, -0.009293260052800179, 0.14538973569869995, -0.08347027003765106, 0.1757643222808838, 0.0420389361679554, -0.05314108356833458, 0.16019463539123535, -0.01330169104039669, -0.0632644072175026, -0.04045012593269348, -0.13077184557914734, 0.10372064262628555, -0.06345800310373306, -0.07204753160476685, -0.015649981796741486, -0.12036480009555817, 0.10379243642091751, 0.12728272378444672, -0.1338253915309906, -0.011252950876951218, -0.1504172384738922, -0.08889010548591614, -0.04083579406142235, 0.05105561390519142, -0.027702240273356438, -0.051140859723091125, 0.037129200994968414, 0.013996327295899391, 0.12710943818092346, 0.1261812150478363, 0.08166596293449402, -0.10382166504859924, 0.10480806231498718, -0.1253989338874817, -0.024674901738762856, -0.14611414074897766, 0.041862595826387405, -0.018693961203098297, 0.03740987926721573, 0.11037249118089676, -0.01473814994096756, -0.019635289907455444, -0.026816731318831444, 0.011464733630418777, 0.06986692547798157, 0.010311342775821686, -0.11251580715179443, -0.0035126525908708572, 0.025614488869905472, -0.04558242857456207, 0.15537163615226746, -0.05103059858083725, -0.07827290147542953, 0.1114322692155838, -0.08063959330320358, 0.042390935122966766, 0.1259024739265442, 0.0034357579424977303, 0.1278230994939804, -0.03620568662881851, -0.08419279754161835, 0.01397009938955307, 0.08684034645557404, -0.009434966370463371, -0.1139792948961258, -0.1732306331396103, 0.07803449034690857, 0.006016463972628117, 0.22635281085968018, -0.008267022669315338, 0.05907032638788223, -0.026760082691907883, 0.10089610517024994, -0.10951966047286987, -0.14404460787773132, -0.1025175079703331, -0.04749178886413574, -0.06802159547805786, 0.061973512172698975, 0.0029269088990986347, 0.028440158814191818, -0.02111837826669216, 0.11016729474067688, 0.008557603694498539, -0.08203566819429398, 0.04720380902290344, 0.06008169800043106, 0.017828745767474174, -0.005787794478237629, 0.02506299875676632, 0.04114494472742081, 0.16410496830940247, 0.08966755867004395, 0.0676392987370491, -0.05114716663956642, -0.06536465138196945, 0.006419275887310505, -0.06808328628540039, -0.02246282622218132, 0.052867043763399124, -0.11513520777225494, -0.029942713677883148, -0.16756394505500793, 0.06597109138965607, -0.0641232281923294, -0.11946651339530945, -0.05347298085689545, -0.014508293941617012, -0.003696751082316041, -0.056179847568273544, 0.056380875408649445, 0.04781980812549591, 0.1677674949169159, 0.15985038876533508, -0.01906363107264042, 0.040686558932065964, 0.02940065786242485, 0.0034170574508607388, -0.13372179865837097, 1.1208833077401826e-32, -0.0014578034169971943, -0.060912683606147766, 0.0025096945464611053, -0.16228002309799194, -0.0623059943318367, 0.051803529262542725, 0.02510800212621689, -0.02627767249941826, -0.03197826072573662, -0.005573648028075695, -0.11118300259113312, 0.0492861308157444, 0.0006072171963751316, 0.07901938259601593, -0.0030405716970562935, -0.2199365198612213, -0.018766306340694427, 0.024912558495998383, 0.08729133009910583, -0.025885891169309616, 0.022562284022569656, -0.11683204770088196, 0.004912183154374361, 0.08530310541391373, 0.11892808973789215, -0.03230712190270424, 0.06527763605117798, 0.14317171275615692, -0.027870234102010727, 0.04413164034485817, -0.04711657017469406, 0.09386773407459259, 0.12074221670627594, -0.018861431628465652, -0.05795050784945488, 0.034807223826646805, 0.007607843726873398, -0.0029087280854582787, 0.01931719481945038, -0.09334371984004974, -0.007228255271911621, 0.13073867559432983, -0.07856989651918411, -0.08325602859258652, -0.03526965528726578, 0.14609713852405548, -0.027784688398241997, -0.0004036072641611099, -0.09725631773471832, 0.026527490466833115, 0.07417632639408112, 0.06423524022102356, -0.06983373314142227, -0.018717855215072632, -0.06374125182628632, -0.008515644818544388, -0.041741400957107544, -0.2145892083644867, 0.01526564545929432, 0.13945195078849792, -0.031219258904457092, 0.16081705689430237, -0.09383270889520645, -0.029809143394231796, -0.3316746652126312, 0.14608871936798096, 0.10623118281364441, 0.06874915957450867, -0.19845856726169586, 0.17449338734149933, 0.01278701052069664, 0.045212455093860626, 0.1531527042388916, -0.07949288934469223, 0.11791304498910904, 0.04055628925561905, -0.02171102911233902, 0.02297176420688629, 0.12612268328666687, 0.011471129953861237, 0.07004225254058838, -0.051768526434898376, 0.2686479091644287, 0.009136402048170567, -0.07738658785820007, -0.09271436929702759, 6.292015314102173e-06, -0.028255265206098557, 0.051386188715696335, -0.1188909113407135, -0.07423752546310425, -0.060258615761995316, 0.08231446892023087, 0.15026694536209106, 0.07336501777172089, -1.0516793839133821e-32, -0.014692015945911407, 0.059844523668289185, -0.08664920926094055, 0.05164916813373566, -0.054067496210336685, 0.042651206254959106, 0.183145672082901, 0.038630977272987366, 0.0007578060030937195, -0.057449452579021454, 0.007724091410636902, -0.03261424973607063, 0.028534909710288048, 0.08916613459587097, 0.07760978490114212, -0.024317491799592972, 0.20771761238574982, -0.006405625492334366, 0.11463133245706558, -0.016598396003246307, -0.0013759899884462357, 0.13227301836013794, -0.15142780542373657, 0.07441677898168564, 0.0853278636932373, -0.04931320250034332, 0.023576613515615463, 0.13531766831874847, -0.06186150759458542, -0.11685508489608765, -0.06352115422487259, -0.07520169019699097, -0.049651019275188446, 0.13537493348121643, 0.0040682414546608925, 0.08725664019584656, 0.007327514700591564, -0.17604462802410126, -0.01813817210495472, -0.09797710925340652, 0.09212769567966461, 0.11908168345689774, 0.014708535745739937, 0.07989238947629929, 0.05728858709335327, 0.09622888267040253, 0.10234476625919342, 0.10382012277841568, 0.1567344069480896, -0.06546146422624588, -0.011068269610404968, 0.056651145219802856, -0.06129077821969986, 0.036362189799547195, -0.03581196442246437, 0.053570494055747986, -0.01660832017660141, 0.008268753066658974, -0.15159378945827484, -0.02296285703778267, -0.07119061797857285, 0.10808585584163666, 0.008955579251050949, -0.06780728697776794, 0.13151733577251434, -0.14783504605293274, 0.015173413790762424, -0.323969304561615, 0.06231553852558136, -0.0028900778852403164, -0.007192600984126329, -0.0282832570374012, -0.06539803743362427, -0.04142177104949951, -0.0634857714176178, 0.149762362241745, -0.11220060288906097, -0.06544776260852814, -0.04141483083367348, 0.10310836881399155, -0.022565778344869614, 0.11070678383111954, -0.05490009859204292, -0.10212503373622894, -0.03373521938920021, 0.11071667075157166, 0.012530900537967682, -0.03188132122159004, -0.036249302327632904, -0.053122926503419876, -0.19983769953250885, -0.1310725212097168, -0.07256775349378586, 0.11366041004657745, 0.10197508335113525, -9.96490854276999e-08, 0.10438573360443115, -0.0848599523305893, -0.11685922741889954, 0.04387274384498596, 0.11287188529968262, 0.06680355966091156, 0.17984655499458313, -0.054462917149066925, 0.06199698895215988, 0.06283662468194962, 0.17964957654476166, 0.07788023352622986, -0.18068167567253113, -0.055543988943099976, -0.17155882716178894, 0.028590023517608643, -0.1303798109292984, -0.08543384075164795, -0.02275405079126358, -0.19105678796768188, 0.11563986539840698, 0.1099618673324585, -0.07390408217906952, -0.028817832469940186, 0.13737359642982483, -0.09372581541538239, -0.0681147575378418, 0.12936927378177643, -0.031099114567041397, 0.026278339326381683, -0.1227700486779213, -0.1647864431142807, -0.06464187800884247, -0.2043401002883911, -1.533166505396366e-05, 0.06609335541725159, 0.06238771975040436, 0.05103491619229317, 0.18596050143241882, 0.09343896061182022, 0.08070574700832367, 0.06672997027635574, 0.03507470339536667, -0.05828835815191269, -0.06645959615707397, -0.14523297548294067, -0.2423166036605835, 0.00202958844602108, 0.06796486675739288, -0.21700109541416168, 0.02689111791551113, -0.05939628556370735, -0.016766462475061417, 0.04937504976987839, 0.17812451720237732, -0.042553387582302094, -0.2306685447692871, -0.0290801003575325, -0.035192228853702545, 0.0935959666967392, 0.06736400723457336, -0.271295964717865, -0.07760725915431976, 0.15071071684360504], "changes": {"1wk": -6.2106662891185636}}, {"text": "Bitcoin ETFs see a record 4 days of outflows Yahoo Finance Tue, Jan 14, 2025, 7:24 PM In This Article: IBIT -0.23% GBTC -0.30% BITO -0.27% BITI +0.21% BITU -0.43% Bitcoin ETFs see a record four days of outflows. Madison Mills joins Morning Brief to outline what investors need to know. To watch more expert insights and analysis on the latest market action, check out more Morning Brief here . This post was written by Naomi Buchanan. Related Videos 00:55 Alphabet earnings, Fed commentary, JOLTS data: What to Watch Yahoo Finance Video \u2022 10 hours ago 21:13 Tariff losses, Palantir outlook: Market Domination Overtime Yahoo Finance Video \u2022 10 hours ago 49:49 Trump's tariff fallout, REIT strategies: Market Domination Yahoo Finance Video \u2022 10 hours ago 04:48 Tariff dip, February markets, bitcoin jumps: Market Takeaways Yahoo Finance Video \u2022 11 hours ago View Comments Terms and Privacy Policy Privacy Dashboard Recommended Stories", "symbol": "BITU", "date": "2025-01-14T16:24:00+00:00", "sentiment": {"score": 0.012186061590909958, "confidence": 0.037778258323669434, "probabilities": {"positive": 0.037778258323669434, "negative": 0.025592196732759476, "neutral": 0.936629593372345}}, "embedding": [-0.014028986915946007, -0.09080027043819427, 0.06253793090581894, 0.04753202199935913, 0.1572679728269577, -0.04014940932393074, 0.031286824494600296, 0.004156181588768959, -0.009155778214335442, -0.01884441077709198, -0.06593243032693863, 0.007462943904101849, -0.04681028053164482, -0.027641678228974342, -0.016740793362259865, -0.00034808332566171885, 0.005436294246464968, -0.05823778361082077, -0.11446650326251984, 0.06416209787130356, -0.07159443944692612, -0.04262372851371765, -0.014510301873087883, 0.004187782760709524, 0.043920185416936874, 0.08771026879549026, -0.033240385353565216, -0.10459581017494202, -0.08029015362262726, -0.09269940853118896, -0.09222842752933502, 0.10502152144908905, -0.024026814848184586, -0.004967404063791037, -0.017219316214323044, -0.0014087968738749623, 0.0652853399515152, 0.09325047582387924, 0.05750991031527519, -0.06362972408533096, 0.00855847354978323, -0.09785758703947067, 0.0025832285173237324, -0.02330285683274269, -0.009835002943873405, 0.005752312019467354, 0.0909070372581482, -0.017773235216736794, 0.08542412519454956, 0.013473276048898697, -0.019729789346456528, 0.13102881610393524, 0.08319224417209625, 0.05818382278084755, -0.06761249899864197, -0.03198124095797539, -0.0014424773398786783, -0.058807965368032455, 0.121394082903862, 0.06552475690841675, -0.0077672190964221954, -0.12675979733467102, -0.004743257537484169, 0.03232847526669502, -0.037858594208955765, 0.013928278349339962, -0.09111522883176804, 0.016982441768050194, -0.053338490426540375, -0.07624512165784836, 0.13108962774276733, -0.0031383358873426914, -0.08087071776390076, -0.0031794521491974592, 0.05772622674703598, -0.0009908067295327783, 0.17019541561603546, -0.00404361030086875, 0.002529084449633956, -0.05336964130401611, 0.06263744086027145, 0.013098453171551228, 0.016848765313625336, -0.08381349593400955, -0.013195221312344074, -0.05523452162742615, 0.08418381959199905, 0.006011312361806631, -0.059087421745061874, -0.046739671379327774, 0.04472969472408295, 0.08750688284635544, -0.029429182410240173, 0.03749728575348854, 0.105984628200531, 0.022949011996388435, -0.062144216150045395, 0.01167516689747572, -0.005288533866405487, 0.02632981538772583, 0.0717804804444313, 0.15328793227672577, -0.12013620883226395, -0.03555408865213394, -0.008757391013205051, -0.112921342253685, -0.051189906895160675, 0.04420509189367294, -0.00804181769490242, -0.003804862964898348, 0.10844738781452179, 0.05107233300805092, -0.02781814895570278, -0.016661101952195168, -0.10379302501678467, -0.02891494147479534, -0.10770086944103241, -0.06277736276388168, -0.00031625982956029475, 0.0628831759095192, 0.044997688382864, 0.15567654371261597, -0.07782585918903351, 0.02971477434039116, -0.05291864648461342, 0.07032578438520432, -0.02721903659403324, 1.7936960869377412e-32, -0.10981534421443939, 0.02328881062567234, -0.036139585077762604, -0.06491678953170776, -0.058006882667541504, 0.024952935054898262, -0.008715873584151268, -0.06609749794006348, -0.022561421617865562, -0.04909004643559456, -0.10675206780433655, 0.08208298683166504, -0.03890474885702133, 0.11965996026992798, -0.038289979100227356, -0.19792400300502777, 0.036259446293115616, -0.04293474555015564, 0.14231476187705994, -0.055470507591962814, 0.08121373504400253, -0.0437929704785347, -0.0677776113152504, 0.020130470395088196, 0.015871435403823853, 0.028342686593532562, 0.026147272437810898, -0.03453746438026428, 0.0557306632399559, 0.039035648107528687, -0.023974761366844177, 0.029371339827775955, -0.018162395805120468, -0.05061009153723717, -0.05727608501911163, 0.0042169829830527306, 0.07695326954126358, 0.005954548716545105, -0.02851160615682602, -0.06092975661158562, -0.10704917460680008, 0.12805189192295074, -0.13616949319839478, -0.01240296009927988, -0.07090117782354355, -0.05300863832235336, 0.013413955457508564, 0.0012445038883015513, 0.00046327506424859166, 0.011201154440641403, -0.05303115025162697, -0.0074860891327261925, 0.0768050029873848, -0.05287524312734604, -0.006438727956265211, -0.019019266590476036, -0.049249086529016495, -0.19417434930801392, 0.023946287110447884, 0.09773412346839905, 0.010214301757514477, 0.03257926553487778, -0.032534558326005936, 0.009863486513495445, -0.17486713826656342, 0.11426641792058945, 0.030222896486520767, 0.06105413660407066, -0.18733739852905273, 0.11458736658096313, 0.0020664907060563564, -0.014987263828516006, 0.01072220504283905, -0.036108266562223434, 0.04837935417890549, -0.0038652087096124887, 0.01641181856393814, 0.06444601714611053, 0.07208742201328278, 0.029243003576993942, 0.0074881138280034065, -0.1033550500869751, 0.2375853806734085, 0.04858159273862839, 0.005652762949466705, -0.024236485362052917, -0.03967355191707611, -0.012477212585508823, 0.006828444078564644, -0.07012202590703964, -0.05258310213685036, -0.019234279170632362, 0.026232615113258362, 0.023590100929141045, 0.01889077015221119, -1.8311563000993643e-32, -0.031858690083026886, 0.09035773575305939, -0.041618622839450836, 0.036513250321149826, -0.0013285900931805372, -0.022321423515677452, 0.029101748019456863, 0.1581602692604065, 0.1317826211452484, 0.017581282183527946, -0.035228267312049866, 0.07686860114336014, 0.015990961343050003, 0.0036281233187764883, -0.043304529041051865, -0.07614096254110336, 0.07369612157344818, -0.04011420160531998, 0.00734052574262023, -0.011811334639787674, -0.04092403128743172, -0.024837708100676537, -0.0100143663585186, 0.02558496594429016, 0.07630829513072968, 0.06270593404769897, -0.027021877467632294, -6.430676148738712e-05, -0.010076072998344898, -0.010919032618403435, -0.05218452587723732, -0.008762110024690628, 0.012271140702068806, 0.1343330293893814, -0.0035820649936795235, 0.08219096064567566, -0.020968452095985413, -0.02734498679637909, 0.02273622713983059, 0.03612298518419266, -0.0015160564798861742, 0.07401168346405029, 0.009784440509974957, -0.014893021434545517, 0.001831679604947567, 0.033331453800201416, -0.08305089920759201, 0.07827937602996826, 0.032944533973932266, 0.01856769248843193, -0.05097346380352974, 0.2042938619852066, 0.02904444746673107, -0.002333210315555334, -0.07121188938617706, -0.05195493996143341, 0.022886646911501884, 0.035364702343940735, -0.07698292285203934, 0.03948725387454033, -0.02230970561504364, 0.060242343693971634, 0.0005133459344506264, 0.0035960148088634014, -0.022546077147126198, -0.047084443271160126, -0.07875129580497742, -0.13638406991958618, 0.04617258161306381, -0.12042795121669769, 0.10275635123252869, -0.0038578242529183626, -0.10336665064096451, -0.1256483793258667, -0.03161398693919182, 0.07014071941375732, 0.01582203432917595, -0.022509431466460228, 0.013987834565341473, 0.08234414458274841, 0.0502987839281559, 0.10318988561630249, 0.010254761204123497, -0.07401242107152939, 0.01948067732155323, 0.0852714404463768, -0.05617782101035118, -0.08306955546140671, 0.008834521286189556, 0.00024937608395703137, -0.08133020251989365, -0.12624554336071014, -0.04640989378094673, 0.12674880027770996, -0.03615187108516693, -1.0035261510665805e-07, -0.008992701768875122, -0.02225404419004917, 0.046482622623443604, 0.047380249947309494, 0.03758878633379936, 0.02165801450610161, 0.025202864781022072, 0.07325839251279831, -0.002326676854863763, -0.0349612757563591, 0.1992538869380951, 0.001065781689248979, -0.18248172104358673, -0.05258044973015785, -0.023928603157401085, -0.026704929769039154, -0.06921305507421494, -0.018977856263518333, 0.013592169620096684, -0.009000678546726704, 0.11568156629800797, 0.049591805785894394, 0.005195641424506903, -0.024851690977811813, 0.018485169857740402, -0.0002723863290157169, 0.01525009423494339, -0.02216188982129097, -0.010029743425548077, -0.027023684233427048, -0.03996260091662407, -0.04805358871817589, -0.03799930587410927, -0.036944665014743805, 0.005626086611300707, 0.09439195692539215, -0.010969957336783409, 0.03929566219449043, 0.0795459896326065, 0.03666972741484642, -0.0959402322769165, -0.021205969154834747, 0.014733719639480114, -0.07446727901697159, -0.07469382137060165, -0.07401249557733536, -0.1798919141292572, 0.018763521686196327, 0.16908244788646698, -0.10352331399917603, -0.004870677832514048, -0.06780557334423065, 0.03262684866786003, 0.0566430501639843, 0.07940042018890381, 0.08859430253505707, -0.12490284442901611, -0.01448556873947382, -0.06032021716237068, -0.010706750676035881, -0.008687740191817284, -0.12985727190971375, -0.1083296462893486, 0.15825791656970978], "changes": {"1wk": 20.56614465445488}}, {"text": "Why the momentum driving bitcoin adoption is just getting started Madison Mills and Brad Smith Fri, Jan 3, 2025, 5:55 PM In This Article: BITW -0.38% SOL-USD +5.49% BTC-USD +3.11% BITU -0.43% IBIT -0.23% While bitcoin ( BTC-USD ) has hovered around $96,000 in the first several days of 2025 \u2014 a pullback from $107,000 in the final weeks of 2024 \u2014 BlackRock's iShares Bitcoin Trust ETF ( IBIT ) saw $333 million in outflows on Thursday. \"Crypto tends to move in these kind of momentum cycles. And so we have to be patient during the quiet times, we have to get excited. So for most investors, you have to think really long term,\" CoinDesk Indices Managing Director Andy Baehr states, pointing to the Federal Reserve's September and November meetings and the US election as events that pushed bitcoin higher in \"clumps.\" Baehr sits down in-studio with Morning Brief hosts Brad Smith and Madison Mills to talk more about crypto adoption, the outlook on US regulatory frameworks, and the general view on bitcoin ETFs moving ahead in 2025. \"The adoption momentum, when you think ahead, is just getting off to a start. And the dialogue change between this time last year and today has been huge. So you can't really look at bitcoin and think of it as something that has a valuation cycle, like a 500-year-old asset. It's still brand new,\" Baehr tells Yahoo Finance. Related Videos 08:45 Why Trump\u2019s Tariff Idol, McKinley, Abandoned His Own Tariff Policy WSJ \u2022 5 hours ago 00:55 Alphabet earnings, Fed commentary, JOLTS data: What to Watch Yahoo Finance Video \u2022 10 hours ago 21:13 Tariff losses, Palantir outlook: Market Domination Overtime Yahoo Finance Video \u2022 10 hours ago 49:49 Trump's tariff fallout, REIT strategies: Market Domination Yahoo Finance Video \u2022 10 hours ago \"Adoption momentum for bitcoin is going to do two things: it's going to continue to support a medium to long term price, and it'll also over time, we believe, help to dampen volatility.\" To watch more expert insights and analysis on the latest market action, check out more Morning Brief here . This post was written by Luke Carberry Mogan . View Comments Terms and Privacy Policy Privacy Dashboard Recommended Stories", "symbol": "BITU", "date": "2025-01-03T14:55:00+00:00", "sentiment": {"score": 0.09220461174845695, "confidence": 0.13944664597511292, "probabilities": {"positive": 0.13944664597511292, "negative": 0.04724203422665596, "neutral": 0.8133113384246826}}, "embedding": [-0.008703367784619331, -0.12409153580665588, 0.03472195565700531, 0.028668027371168137, 0.15022850036621094, -0.062470778822898865, -0.04401808977127075, 0.04037748649716377, 0.07832635194063187, 0.0011728229001164436, -0.08561621606349945, 0.03398634120821953, 0.018643170595169067, -0.01416166964918375, 0.041198328137397766, 0.00532286474481225, 0.0027470579370856285, -0.08422098308801651, -0.20166939496994019, 0.1418040692806244, -0.03537248447537422, -0.06601596623659134, 0.009419011883437634, -0.0054063089191913605, -0.012102574110031128, 0.11623019725084305, -0.06331101804971695, -0.09496623277664185, -0.10951156169176102, 0.0035186277236789465, -0.05157504975795746, 0.12389624118804932, -0.022047676146030426, -0.0035835430026054382, -0.04829652979969978, 0.00029292190447449684, 0.13363520801067352, 0.12065622210502625, 0.05894099175930023, -0.09684517979621887, -0.021399103105068207, -0.1438279002904892, -0.06239893287420273, -0.05295361950993538, -0.018272951245307922, -0.036324068903923035, 0.09485036134719849, 0.01577657088637352, 0.031284913420677185, -0.03222030773758888, -0.1001296192407608, -0.01903635635972023, 0.015928136184811592, 0.0217866413295269, -0.05575913190841675, -0.01712794043123722, 0.08631792664527893, 0.031448692083358765, 0.08329463005065918, -0.031367648392915726, -0.035019632428884506, -0.055175021290779114, -0.021323155611753464, 0.018520642071962357, 0.06757915765047073, 0.016341160982847214, 0.03234392777085304, 0.018700197339057922, -0.0490267388522625, 0.04234425351023674, 0.14471305906772614, -0.09499572217464447, -0.06947454810142517, 0.045505814254283905, 0.04458335041999817, -0.0016377080464735627, 0.20860207080841064, 0.005954439286142588, 0.05489693582057953, -0.09748055040836334, 0.03263276815414429, 0.03763734549283981, 0.05882563069462776, -0.14602601528167725, -0.07891024649143219, -0.006289028562605381, 0.008932340890169144, -0.009492254815995693, -0.05753963813185692, -0.07351966202259064, 0.034526195377111435, -0.040295153856277466, -0.09792499989271164, 0.08950182795524597, 0.15268954634666443, 0.0025368959177285433, -0.07119755446910858, 0.08580470085144043, 0.01606680639088154, 0.05971870198845863, 0.02684204839169979, 0.07898908853530884, -0.1112733855843544, -0.044257648289203644, -0.009306536987423897, -0.0661018118262291, -0.03287729620933533, -0.017931517213582993, -0.01353456825017929, -0.014884170144796371, -0.03232407569885254, -0.024757232517004013, -0.07493474334478378, -0.011035164818167686, -0.052580080926418304, -0.08391954749822617, -0.07846598327159882, -0.021373875439167023, 0.03703524172306061, 0.03273528814315796, 0.12956960499286652, 0.14240069687366486, -0.10859644412994385, 0.028876811265945435, 0.023656921461224556, -0.050038840621709824, -0.08616361021995544, 1.19630853541871e-32, -0.10453754663467407, -0.007587323896586895, -0.0565226748585701, 0.008894478902220726, -0.11710803210735321, 0.11308898031711578, 0.03400351107120514, 0.030480224639177322, -0.05762909725308418, -0.07556501030921936, 0.016307998448610306, 0.06755457818508148, -0.07182632386684418, -0.007105585187673569, 0.04116946458816528, -0.22300338745117188, -0.10407592356204987, -0.07034308463335037, 0.18247298896312714, -0.06197666749358177, 0.05247165635228157, 0.02995147742331028, -0.0501689538359642, -0.045217860490083694, 0.009004563093185425, 0.05567508935928345, 0.04996635019779205, 0.021633107215166092, 0.001089043915271759, 0.06853388249874115, -0.07969724386930466, 0.06389673054218292, -0.06321639567613602, -0.10149313509464264, -0.03705400228500366, -0.035793401300907135, 0.07109322398900986, -0.05873841047286987, -0.040136683732271194, -0.14269134402275085, -0.04943797364830971, 0.0788939818739891, -0.2224048674106598, 0.033368173986673355, -0.004938692320138216, 0.05014082416892052, 0.06595277786254883, 0.03270301595330238, -0.0429416298866272, 0.002407998312264681, 0.056413911283016205, -0.01710907183587551, 0.005232912953943014, -0.0738208144903183, -0.07517249137163162, -0.10476337373256683, -0.05461829900741577, -0.2211126983165741, -0.05653052031993866, 0.01272558979690075, 0.028520848602056503, 0.05044369399547577, -0.006914917379617691, 0.06651526689529419, -0.1275220811367035, 0.19222700595855713, -0.010395696386694908, 0.11625877022743225, -0.19098606705665588, 0.1727723777294159, -0.057235438376665115, -0.024341098964214325, -0.01534406840801239, -0.042874258011579514, 0.03900784254074097, -0.040046315640211105, 0.02784661203622818, 0.05231418088078499, 0.08149714022874832, 0.03397304564714432, -0.033199384808540344, -0.0651216208934784, 0.16835448145866394, 0.04247420281171799, -0.028711088001728058, -0.010337229818105698, -0.010505115613341331, -0.051731258630752563, 0.05600859224796295, -0.13763269782066345, -0.04069369658827782, -0.06532159447669983, 0.04796675965189934, 0.19490762054920197, 0.019523687660694122, -1.3574649905598055e-32, 0.019797131419181824, -0.059739403426647186, -0.03165927156805992, 0.1604405641555786, -0.0464363694190979, -0.0561060830950737, 0.03077506273984909, 0.032136671245098114, -0.02861791104078293, -0.14691975712776184, -0.028028827160596848, -0.002682287245988846, 0.05951029062271118, 0.12237287312746048, -0.03779047727584839, -0.05334647372364998, 0.039658546447753906, -0.06736226379871368, -0.0477178618311882, -0.03632132709026337, -0.00211517745628953, 0.06818222254514694, -0.16819021105766296, -0.006705178879201412, 0.008508956991136074, 0.00834450963884592, -0.01943415030837059, 0.044239550828933716, 0.08682084828615189, -0.030898986384272575, -0.09431952983140945, 0.02224934659898281, -0.024883219972252846, -0.03209347650408745, 0.019768817350268364, 0.12959420680999756, -0.05167485401034355, -0.06246648728847504, -0.05233147740364075, -0.0004795673303306103, -0.018620586022734642, 0.05211154744029045, 0.011767081916332245, -0.07053832709789276, 0.047049932181835175, 0.08030560612678528, 0.12069831043481827, 0.19008538126945496, 0.08735711872577667, 0.04095271974802017, 0.1432102918624878, 0.16514423489570618, 0.0701221227645874, -0.04852531850337982, -0.07841268926858902, 0.05552592873573303, 0.017819806933403015, 0.042459212243556976, -0.02321135625243187, 0.04230400174856186, -0.020269781351089478, 0.1877426952123642, 0.07766566425561905, -0.005664888769388199, 0.03574385493993759, -0.01814132183790207, -0.06738782674074173, -0.09273280203342438, 0.05418402701616287, -0.05167935788631439, 0.021717919036746025, -0.05637466907501221, -0.06432811915874481, -0.09366784244775772, -0.03445860743522644, 0.0776393711566925, 0.04917103052139282, -0.09777336567640305, -0.009997270070016384, 0.04351101815700531, -0.06385625153779984, 0.1367199718952179, 0.058330461382865906, -0.08990590274333954, -0.008718197233974934, 0.10461068153381348, -0.08269581198692322, -0.043748266994953156, -0.04102133959531784, -0.007665893062949181, -0.11250843107700348, -0.15495312213897705, -0.06821814179420471, 0.08850450813770294, -0.1063687652349472, -1.006327750019409e-07, -0.006697302684187889, -0.0025689834728837013, 0.016800304874777794, -0.022351037710905075, 0.16752906143665314, 0.038944363594055176, 0.05963439494371414, -0.021264340728521347, 0.08134206384420395, 0.09974110871553421, 0.2620149254798889, 0.04290182515978813, -0.13675612211227417, 0.01584843546152115, -0.08787417411804199, 0.09145946800708771, -0.12657970190048218, -0.09628956019878387, 0.002574024721980095, 0.018664609640836716, 0.1283370703458786, -0.01626037061214447, -0.005387047305703163, -0.03879942744970322, 0.10075844079256058, -0.055390167981386185, -0.08509242534637451, 0.09756849706172943, -0.011703700758516788, 0.006749746389687061, -0.04167398810386658, -0.06692428141832352, -0.018694283440709114, -0.040489986538887024, 0.02376459166407585, 0.06685251742601395, 0.037207189947366714, 0.08766750991344452, 0.06697564572095871, 0.005427957978099585, -0.015613758936524391, 0.013693533837795258, 0.038142476230859756, -0.04094638302922249, -0.05614551529288292, -0.12236280739307404, -0.13365420699119568, 0.07798153907060623, 0.10104048252105713, -0.07416021078824997, -0.06296418607234955, -0.10159476101398468, 0.046646080911159515, 0.038354936987161636, 0.1347394585609436, 0.026111319661140442, -0.12182961404323578, -0.039547860622406006, -0.11526061594486237, 0.09283903986215591, 0.046775996685028076, -0.14248031377792358, 0.05634120851755142, 0.1675834059715271], "changes": {"1wk": -8.32419935194571, "1mo": 3.5231894489617224}}, {"text": "The CAJ's mentorship program is back! CNW Group Tue, Dec 3, 2024, 5:00 PM 2 min read TORONTO , Dec. 3, 2024 /CNW/ -The Canadian Association of Journalists (CAJ) is pleased to announce its popular mentorship is back and now accepting applications. The CAJ is Canada's largest national professional organization for journalists from all media, representing members across the country. The CAJ's primary roles are to provide high-quality professional development for its members and public-interest advocacy. (CNW Group/Canadian Association of Journalists) \"Give yourself the gift of mentorship this holiday season,\" said Brent Jolly , CAJ president. \"The CAJ's mentorship program is a priceless opportunity for journalists to build professional connections and to nurture their development for years to come.\" The Autumn 2024 round marks the 11th round of the mentorship program, which began in 2020. Over the past four years, hundreds of journalists from across Canada have been matched with mentors. Mentors have worked with mentees to overcome practical and methodological challenges to tell incredible stories while strengthening confidence and community. The Autumn 2024 program once again sees 30 top Canadian journalists working in radio, television, digital, and print publications from across the country volunteer their time to provide guidance and expertise to colleagues who are in the early and middle portions of their careers. The full roster of mentors for this round is: Shireen Ahmed - Columnist, CBC Sports Drew Anderson - Alberta - Saskatchewan reporter, The Narwhal Patricia Bitu-Tshikudi - Morning radio show host, ICI Manitoba Laurence Brisson Dubreuil - Video journalist, CTV News Montreal Rachel Browne - Freelance journalist Darren Calabrese - Freelance photojournalist Adrian Ghobrial - Senior correspondent, CTV National News Mike Hager - B.C reporter, The Globe and Mail Nicholas Hune-Brown - Executive editor, The Local Paul Hunter - Journalist, CBC News Godlove Kamwa - TV host, ICI Manitoba Tamara Khandaker - Podcast producer, Al Jazeera Steve Lambert - Winnipeg correspondent, The Canadian Press Adrian Lee - Opinion editor, The Globe and Mail Geoff Leo - Investigative reporter, CBC News Clara Loiseau - Journalist, Journal de Montr\u00e9al Maggie Macintosh - Education reporter, Winnipeg Free Press Samira Mohyeddin - Founder, On The Line Media Colin Perkel - Retired journalist, formerly with The Canadian Press Sa\u0161a Petricic - Senior foreign correspondent, CBC News Aarti Pole - Network anchor, CBC News Sarah Rieger - News writer, WealthSimple Media Manjula Selvarajah - National technology columnist, CBC Radio Matt Simmons - Journalist, The Narwhal Donna Sound - Reporter, CTV National News Liz Sullivan - Deputy editor of visuals, The Globe and Mail Salim Valji - Calgary reporter, TSN Connie Walker - Investigative journalist Marika Wheeler - Journalist, Radio-Canada Jen Zoratti - Arts reporter and columnist, Winnipeg Free Press Story Continues The deadline for applications to this round of the mentorship program is 11:59 pm ET on Friday, December 6, 2024 . For full details on the program, including mentor bios and a link to the application form, visit our mentorship website page . The CAJ's mentorship program is only open to members of the association in good standing. If you aren't already a CAJ member, we can fix that . Successful applicants will meet with a mentor for one hour per week over the course of the six-week program. The CAJ will be running the next round of its mentorship program in Spring 2025. The Canadian Association of Journalists is a professional organization that serves to advance the interests of journalists from coast to coast to coast. The CAJ's primary roles are public-interest advocacy work and professional development for its members. SOURCE Canadian Association of Journalists Cision View original content to download multimedia: http://www.newswire.ca/en/releases/archive/December2024/03/c2570.html View Comments Terms and Privacy Policy Privacy Dashboard Recommended Stories", "symbol": "BITU", "date": "2024-12-03T14:00:00+00:00", "sentiment": {"score": 0.14833387453109026, "confidence": 0.15941180288791656, "probabilities": {"positive": 0.15941180288791656, "negative": 0.011077928356826305, "neutral": 0.8295102119445801}}, "embedding": [-0.10446801036596298, -0.05375596135854721, -0.004287621006369591, -0.030682172626256943, 0.02021016553044319, 0.06931713968515396, -0.047621723264455795, 0.0032024644315242767, 0.061541371047496796, 0.0763290673494339, -0.10497081279754639, -0.034271351993083954, 0.08409610390663147, 0.029382791370153427, -0.015339095145463943, -0.10621415078639984, -0.07863624393939972, -0.03948116675019264, -0.1485571414232254, -0.025970321148633957, -0.17564301192760468, -0.0818096324801445, 0.06224173307418823, -0.08030468225479126, 0.029157938435673714, -0.055003222078084946, -0.10590960085391998, -0.10934937000274658, -0.136130690574646, 0.048198238015174866, -0.0023876065388321877, 0.13321125507354736, 0.009639598429203033, 0.10647405683994293, 0.08845722675323486, 0.17830675840377808, 0.005507208406925201, 0.004340130835771561, -0.08025950193405151, 0.05435441434383392, 0.09472792595624924, 0.0053678760305047035, -0.08416619896888733, 0.06786049902439117, 0.07072702795267105, -0.15515610575675964, -0.08234366774559021, 0.00784282572567463, -0.08159124106168747, 0.07866530120372772, -0.13264209032058716, -0.09782075881958008, 0.042252685874700546, 0.09484931826591492, 0.04161728918552399, 0.02259751781821251, -0.025864921510219574, 0.05071064829826355, 0.06748269498348236, 0.03353511914610863, -0.033924855291843414, -0.11322355270385742, -0.1670401245355606, 0.0266732145100832, 0.014134250581264496, -0.032163359224796295, -0.05110929161310196, 0.07441461086273193, 0.032196953892707825, -0.11266114562749863, 0.015368510968983173, -0.031091200187802315, 0.06397103518247604, 0.039802826941013336, 0.0350382961332798, -0.008490961976349354, 0.11107052862644196, -0.03849199786782265, 0.14538468420505524, -0.030515993013978004, 0.09675438702106476, -0.030883705243468285, 0.09541669487953186, -0.0377274714410305, -0.07569733262062073, -0.11964398622512817, 0.03282575309276581, -0.047452352941036224, 0.01511463150382042, 0.16964784264564514, -0.01952173188328743, 0.05742176994681358, 0.05966731160879135, -0.04144308343529701, -0.053963106125593185, -0.009309951215982437, 0.21368131041526794, -0.014006354846060276, -0.0022406987845897675, 0.1153930127620697, 0.01434672623872757, -0.019115718081593513, 0.05248253419995308, -0.050688743591308594, -0.05848870426416397, -0.07068589329719543, -0.04283089563250542, -0.07634630799293518, -0.07945448160171509, -0.028742104768753052, -0.06339568644762039, 0.21936316788196564, -0.0964447408914566, -0.06213871389627457, 0.0617377907037735, 0.15412339568138123, -0.05781526118516922, 0.1509781777858734, 0.026167787611484528, 0.003362812101840973, -0.07032452523708344, 0.17404544353485107, -0.07057223469018936, -0.02851414680480957, 0.03963039070367813, -0.036762963980436325, -0.035697005689144135, 7.616103571426435e-33, -0.055732108652591705, 0.10505425184965134, 0.08136449754238129, 0.03946824371814728, 0.033217236399650574, 0.04795099049806595, -0.02776658907532692, 0.10505639761686325, -0.1117406040430069, -0.1459820568561554, 0.05823413282632828, 0.11484131217002869, -0.027578437700867653, 0.036489322781562805, -0.04705139622092247, -0.01316104456782341, -0.12814879417419434, -0.06687068194150925, -0.07957645505666733, 0.06665205210447311, 0.16110864281654358, -0.14993004500865936, -0.0008992203511297703, 0.13286752998828888, 0.08996302634477615, 0.0278766006231308, 0.10000409930944443, -0.0840144008398056, -0.012012319639325142, 0.041993193328380585, -0.07542138546705246, 0.02641262672841549, -0.021988876163959503, -0.06363295018672943, 0.03328792005777359, -0.07994599640369415, 0.06543584167957306, -0.10050322115421295, -0.0033204853534698486, 0.03355688601732254, -0.10931895673274994, -0.0032286341302096844, 0.006553965155035257, -0.07420990616083145, -0.04291411489248276, 0.0448770672082901, 0.047679148614406586, -0.08390012383460999, 0.07235024124383926, 0.1305190771818161, 0.02998049557209015, 0.015093453228473663, -0.01228688471019268, -0.11124778538942337, 0.03495066985487938, 0.09538725018501282, 0.11427614092826843, -0.08466637134552002, 0.007869369350373745, -0.15770944952964783, 0.20342719554901123, -0.03164203464984894, -0.11288256198167801, 0.015156302601099014, -0.007618393748998642, -0.012828092090785503, -0.04598921164870262, -0.0584913045167923, 0.12731687724590302, -0.06770037859678268, -0.13364949822425842, 0.04271519556641579, 0.06985224783420563, -0.04897730052471161, 0.037425361573696136, 0.09559319913387299, -0.09606809914112091, -0.0797933042049408, 0.10821538418531418, 0.0519695058465004, -0.07118439674377441, 0.11381466686725616, 0.007174453232437372, -0.043622709810733795, -0.02046896144747734, -0.08399762958288193, 0.073070228099823, -0.032580696046352386, -0.007876445539295673, 0.04232008755207062, 0.03649108484387398, -0.04902580380439758, 0.18160980939865112, 0.164911150932312, -0.04616571217775345, -7.342510934692394e-33, 0.04453729838132858, -0.030111877247691154, -0.14476588368415833, -0.015157567337155342, 0.1489495038986206, -0.06226388365030289, -0.031038079410791397, 0.152048259973526, 0.13185277581214905, -0.07265117764472961, 0.09305144846439362, -0.09027263522148132, -0.08707599341869354, 0.15897762775421143, -0.11535200476646423, 0.008154269307851791, -0.03651858866214752, 0.044179584830999374, -0.29724812507629395, -0.054898105561733246, 0.13511987030506134, 0.08661552518606186, -0.08688757568597794, 0.08465704321861267, 0.12853750586509705, -0.007517971098423004, 0.21846219897270203, 0.03270503133535385, -0.07471602410078049, 0.0683116763830185, -0.15803124010562897, 0.01279317308217287, -0.1358776092529297, 0.02365749329328537, -0.04106421768665314, 0.11463072896003723, 0.045579034835100174, -0.10252107679843903, -0.14103272557258606, 0.1735348105430603, 0.15708604454994202, -0.022320475429296494, -0.07984494417905807, 0.0025647785514593124, -0.08633489906787872, 0.0019516360480338335, 0.09719385206699371, 0.08969022333621979, -0.022060606628656387, 0.034538425505161285, -0.042727984488010406, -0.0008025243878364563, -0.09302487969398499, 0.11845743656158447, 0.11298658698797226, 0.07478385418653488, 0.10182454437017441, -0.10299420356750488, -0.05143749713897705, -0.07529985159635544, -0.021364018321037292, 0.09726150333881378, -0.004503239877521992, -0.02460840716958046, 0.20847728848457336, -0.049532052129507065, -0.030015863478183746, -0.03183228150010109, 0.007339907810091972, 0.05937769263982773, -0.024694863706827164, -0.05425623059272766, -0.08000320196151733, -0.21088406443595886, -0.04127144441008568, 0.10637842863798141, -0.06535593420267105, -0.05507776141166687, -0.07586924731731415, -0.07330179214477539, -0.04967084899544716, -0.02212371490895748, 0.02200101688504219, 0.208281010389328, 0.11949487030506134, 0.0607682466506958, 0.07564234733581543, -0.06221792846918106, 0.044942889362573624, 0.11314257979393005, 0.04303416609764099, -0.059937961399555206, 0.007083428092300892, 0.10761352628469467, 0.017148036509752274, -9.980222159811092e-08, -0.16545885801315308, 0.021270181983709335, -0.31893205642700195, -0.037884168326854706, 0.10563264787197113, -0.07134666293859482, -0.02847128175199032, -0.08584453165531158, 0.07177012413740158, 0.1513577699661255, 0.14206431806087494, 0.019704800099134445, -0.07735287398099899, -0.041369616985321045, 0.16067996621131897, 0.0692332535982132, -0.040254704654216766, 0.06243470311164856, -0.09115171432495117, -0.07357120513916016, -0.091562420129776, -0.02043212205171585, -0.1301439106464386, 0.10419175028800964, 0.03984912484884262, -0.08817854523658752, -0.07182011008262634, 0.17769558727741241, 0.12930826842784882, -0.0770358294248581, -0.2048717439174652, 0.047951966524124146, -0.13325661420822144, -0.10019920766353607, 0.022090766578912735, -0.016175651922822, 0.012158466503024101, -0.026387330144643784, 0.04290235787630081, 0.2202444076538086, -0.005466345697641373, -0.05069692060351372, 0.023114632815122604, 0.08971259742975235, -0.013642272911965847, 0.00409806240350008, -0.07078131288290024, 0.022235315293073654, 0.1187903881072998, -0.13991449773311615, -0.1274900883436203, -0.07121150195598602, 0.0553300678730011, -0.016789065673947334, -0.05576813593506813, 0.24345068633556366, -0.03439914435148239, 0.01299411803483963, -0.06857717782258987, 0.038723621517419815, -0.023985400795936584, -0.05522661656141281, -0.031471457332372665, 0.0022600125521421432], "changes": {"1wk": 0.05535898340331203, "1mo": -8.793841059502599}}]